openfinance/__init__.py
openfinance/agentflow/__init__.py
openfinance/agentflow/base_parser.py
openfinance/agentflow/flow/__init__.py
openfinance/agentflow/flow/agent_base.py
openfinance/agentflow/flow/base.py
openfinance/agentflow/llm/__init__.py
openfinance/agentflow/llm/aliyungpt.py
openfinance/agentflow/llm/base.py
openfinance/agentflow/llm/chatgpt.py
openfinance/agentflow/llm/ernie.py
openfinance/agentflow/llm/manager.py
openfinance/agentflow/llm/webgpt.py
openfinance/agentflow/memory/__init__.py
openfinance/agentflow/memory/base.py
openfinance/agentflow/prompt/__init__.py
openfinance/agentflow/prompt/base.py
openfinance/agentflow/skill/__init__.py
openfinance/agentflow/skill/base.py
openfinance/agentflow/tool/__init__.py
openfinance/agentflow/tool/base.py
openfinance/agents/__init__.py
openfinance/agents/callback.py
openfinance/agents/agent/__init__.py
openfinance/agents/agent/agent_prompt.py
openfinance/agents/agent/base.py
openfinance/agents/agent/output_parser.py
openfinance/agents/promptflow/__init__.py
openfinance/agents/promptflow/crawl/__init__.py
openfinance/agents/promptflow/crawl/base.py
openfinance/agents/promptflow/crawl/prompt.py
openfinance/agents/promptflow/data_analysis/__init__.py
openfinance/agents/promptflow/data_analysis/base.py
openfinance/agents/promptflow/data_analysis/output_parser.py
openfinance/agents/promptflow/data_analysis/prompt.py
openfinance/agents/promptflow/entity/__init__.py
openfinance/agents/promptflow/entity/base.py
openfinance/agents/promptflow/entity/output_parser.py
openfinance/agents/promptflow/entity/prompt.py
openfinance/agents/promptflow/factor/__init__.py
openfinance/agents/promptflow/factor/base.py
openfinance/agents/promptflow/function/__init__.py
openfinance/agents/promptflow/function/base.py
openfinance/agents/promptflow/function/output_parser.py
openfinance/agents/promptflow/function/prompt.py
openfinance/agents/promptflow/function/multi_function/__init__.py
openfinance-3.3.6.dist-info/LICENSE
openfinance-3.3.6.dist-info/METADATA
openfinance-3.3.6.dist-info/WHEEL
openfinance-3.3.6.dist-info/top_level.txt
openfinance-3.3.6.dist-info/RECORD
