Metadata-Version: 2.1
Name: openfinance
Version: 3.3.6
Summary: an open financial agent framework powered by llm
Home-page: 
Author: Bin ZHU
Author-email: zhubin_n@outlook.com
Classifier: Programming Language :: Python :: 3.9
Classifier: License :: OSI Approved :: MIT License
Classifier: Operating System :: OS Independent
License-File: LICENSE
Requires-Dist: openai
Requires-Dist: faiss-cpu
